parliamentarian/__init__.py
parliamentarian/cli.py
parliamentarian/config.yaml
parliamentarian/finding.py
parliamentarian/iam_definition.json
parliamentarian/misc.py
parliamentarian/policy.py
parliamentarian/statement.py
parliamentarian/community_auditors/__init__.py
parliamentarian/community_auditors/advanced_policy_elements.py
parliamentarian/community_auditors/config_override.yaml
parliamentarian/community_auditors/credentials_exposure.py
parliamentarian/community_auditors/permissions_management.py
parliamentarian/community_auditors/privilege_escalation.py
parliamentarian/community_auditors/sensitive_access.py
parliamentarian/community_auditors/single_value_condition_too_permissive.py
parliamentarian-1.0.0.dist-info/LICENSE
parliamentarian-1.0.0.dist-info/METADATA
parliamentarian-1.0.0.dist-info/WHEEL
parliamentarian-1.0.0.dist-info/entry_points.txt
parliamentarian-1.0.0.dist-info/top_level.txt
parliamentarian-1.0.0.dist-info/zip-safe
parliamentarian-1.0.0.dist-info/RECORD
