Metadata-Version: 2.1
Name: parliamentarian
Version: 1.0.0
Summary: parliamentarian audits your AWS IAM policies
Home-page: https://github.com/TheClimateCorporation/parliamentarian
Author: Climate LLC
Author-email: cloudeng@climate.com
License: BSD 3
Keywords: aws parliamentarian iam lint audit
Classifier: License :: OSI Approved :: BSD License
Classifier: Programming Language :: Python :: 3
Classifier: Programming Language :: Python :: 3.6
Classifier: Programming Language :: Python :: 3.7
Classifier: Programming Language :: Python :: 3.8
Classifier: Programming Language :: Python :: 3.9
Classifier: Programming Language :: Python :: 3.10
Classifier: Programming Language :: Python :: 3.11
Classifier: Programming Language :: Python :: 3 :: Only
Classifier: Development Status :: 5 - Production/Stable
Requires-Python: >=3.6
License-File: LICENSE
Requires-Dist: boto3
Requires-Dist: jmespath
Requires-Dist: pyyaml
Requires-Dist: json-cfg
Provides-Extra: dev
Requires-Dist: coverage ; extra == 'dev'
Requires-Dist: nose ; extra == 'dev'
Requires-Dist: autoflake ; extra == 'dev'
Requires-Dist: autopep8 ; extra == 'dev'
Requires-Dist: pylint ; extra == 'dev'
